wownlp/__init__.py
wownlp/ner/__init__.py
wownlp/ner/data.py
wownlp/ner/util.py
wownlp-0.0.2.dist-info/LICENSE
wownlp-0.0.2.dist-info/METADATA
wownlp-0.0.2.dist-info/WHEEL
wownlp-0.0.2.dist-info/top_level.txt
wownlp-0.0.2.dist-info/RECORD
