Metadata-Version: 2.1
Name: wownlp
Version: 0.0.2
Summary: Wow! Fast NLP.
Author-email: minskiter <minskiter@gmail.com>
Project-URL: Homepage, https://github.com/minskiter/wownlp
Project-URL: Issues, https://github.com/minskiter/wownlp/issues
Classifier: Programming Language :: Python :: 3
Classifier: License :: OSI Approved :: MIT License
Classifier: Operating System :: OS Independent
Requires-Python: >=3.8
License-File: LICENSE
Requires-Dist: tqdm >=4.0.0
